xontrib/whole_word_jumping.py
xontrib_whole_word_jumping-0.0.1.dist-info/LICENSE
xontrib_whole_word_jumping-0.0.1.dist-info/METADATA
xontrib_whole_word_jumping-0.0.1.dist-info/WHEEL
xontrib_whole_word_jumping-0.0.1.dist-info/top_level.txt
xontrib_whole_word_jumping-0.0.1.dist-info/RECORD
