Metadata-Version: 2.1
Name: xontrib-whole-word-jumping
Version: 0.0.1
Summary: Jump/delete across whole (non-whitespace) words with Ctrl+Left/Right/Delete/Backspace.
Author-email: xontrib-whole-word-jumping <no@no.no>
License: MIT License
Project-URL: Homepage, https://github.com/xonsh/xontrib-whole-word-jumping
Project-URL: Documentation, https://github.com/xonsh/xontrib-whole-word-jumping/blob/master/README.md
Project-URL: Code, https://github.com/xonsh/xontrib-whole-word-jumping
Project-URL: Issue tracker, https://github.com/xonsh/xontrib-whole-word-jumping/issues
Platform: any
Classifier: Programming Language :: Python :: 3
Classifier: License :: OSI Approved :: MIT License
Classifier: Operating System :: OS Independent
Classifier: Topic :: System :: Shells
Classifier: Topic :: System :: System Shells
Classifier: Topic :: Terminals
Requires-Python: >=3.8
License-File: LICENSE
Requires-Dist: xonsh (>=0.12.5)
Requires-Dist: prompt-toolkit (>=3.0.29)
Provides-Extra: dev
Requires-Dist: pytest (>=7.0) ; extra == 'dev'
